dbstorage/__init__.py
dbstorage/admin.py
dbstorage/models.py
dbstorage/storage.py
dbstorage/tests.py
dbstorage/urls.py
dbstorage/views.py
dbstorage/migrations/0001_initial.py
dbstorage/migrations/0002_storedfile_trusted.py
dbstorage/migrations/0003_auto_20180315_1252.py
dbstorage/migrations/__init__.py
django_database_storage_backend-1.0.0.dist-info/LICENSE
django_database_storage_backend-1.0.0.dist-info/METADATA
django_database_storage_backend-1.0.0.dist-info/WHEEL
django_database_storage_backend-1.0.0.dist-info/top_level.txt
django_database_storage_backend-1.0.0.dist-info/RECORD
