Metadata-Version: 2.1
Name: django-database-storage-backend
Version: 1.0.0
Summary: A Django 1.10+/2.x storages backend backed by your existing database.
Home-page: https://github.com/JoshData/django-database-storage-backend
Author: Joshua Tauberer
Author-email: jt@occams.info
License: CC0
Keywords: Django storage database backend
Platform: UNKNOWN
Classifier: Intended Audience :: Developers
Classifier: Topic :: Software Development :: Libraries :: Python Modules
Classifier: Programming Language :: Python :: 3
Classifier: Programming Language :: Python :: 3.4
Classifier: Programming Language :: Python :: 3.5
Classifier: Programming Language :: Python :: 3.6
Provides: dbstorage
Requires-Dist: filemagic
